Metadata-Version: 2.1
Name: quarchpy
Version: 2.2.14
Summary: This packpage offers Python support for Quarch Technology modules.
Author: Quarch Technology ltd
Author-email: support@quarch.com
License: Quarch Technology ltd
Keywords: quarch quarchpy torridon
Classifier: Intended Audience :: Information Technology
Classifier: Intended Audience :: Developers
Classifier: Natural Language :: English
Classifier: Operating System :: MacOS
Classifier: Operating System :: Microsoft :: Windows
Classifier: Operating System :: POSIX
Classifier: Programming Language :: Python
Classifier: Topic :: Scientific/Engineering :: Information Analysis
Classifier: Topic :: System
Classifier: Topic :: System :: Power (UPS)
Requires-Dist: zeroconf>=0.23.0
Requires-Dist: numpy
Requires-Dist: pandas
Requires-Dist: requests
Requires-Dist: packaging
